{"v":4,"entries":{"component-easycascader--defalut":{"type":"story","id":"component-easycascader--defalut","name":"Defalut","title":"component/EasyCascader","importPath":"./src/EasyCascader/index.stories.tsx","tags":["story"]},"component-easycascadercolumn--defalut":{"type":"story","id":"component-easycascadercolumn--defalut","name":"Defalut","title":"component/EasyCascaderColumn","importPath":"./src/EasyCascaderColumn/index.stories.tsx","tags":["story"]},"easycascaderinput--defalut":{"type":"story","id":"easycascaderinput--defalut","name":"Defalut","title":"EasyCascaderInput","importPath":"./src/EasyCascaderInput/index.stories.tsx","tags":["story"]},"easycascaderinput--display-path":{"type":"story","id":"easycascaderinput--display-path","name":"Display Path","title":"EasyCascaderInput","importPath":"./src/EasyCascaderInput/index.stories.tsx","tags":["story"]},"component-easyhighlight--default":{"type":"story","id":"component-easyhighlight--default","name":"Default","title":"component/EasyHighlight","importPath":"./src/EasyHighlight/index.stories.tsx","tags":["story"]},"component-easyhighlight--focus":{"type":"story","id":"component-easyhighlight--focus","name":"Focus","title":"component/EasyHighlight","importPath":"./src/EasyHighlight/index.stories.tsx","tags":["story"]},"component-easylist--defalut":{"type":"story","id":"component-easylist--defalut","name":"Defalut","title":"component/EasyList","importPath":"./src/EasyList/index.stories.tsx","tags":["story"]},"component-easylist--keyboard":{"type":"story","id":"component-easylist--keyboard","name":"Keyboard","title":"component/EasyList","importPath":"./src/EasyList/index.stories.tsx","tags":["story"]},"component-easypopper--defalut":{"type":"story","id":"component-easypopper--defalut","name":"Defalut","title":"component/EasyPopper","importPath":"./src/EasyPopper/index.stories.tsx","tags":["story"]}}}
